setup.py
sniorfy/__init__.py
sniorfy/magicserver.py
sniorfy/rpc.py
sniorfy/stpserver.py
sniorfy.egg-info/PKG-INFO
sniorfy.egg-info/SOURCES.txt
sniorfy.egg-info/dependency_links.txt
sniorfy.egg-info/top_level.txt
sniorfy/ioloop/__init__.py
sniorfy/ioloop/ioloop.py
sniorfy/ioloop/iostream.py
sniorfy/ioloop/netutil.py
sniorfy/ioloop/posix.py
sniorfy/ioloop/process.py
sniorfy/ioloop/stack_context.py