Metadata-Version: 1.1
Name: sniorfy
Version: 0.2.0
Summary: sniorfy is an open source rpc framework in python
Home-page: http://www.simpletp.org/sniorfy
Author: dccmx
Author-email: dccmx@dccmx.com
License: MIT
Download-URL: https://github.com/dccmx/sniorfy/tarball/0.2.0
Platform: UNKNOWN
